syncall/__init__.py
syncall/__version__.py
syncall/aggregator.py
syncall/app_utils.py
syncall/asana/__init__.py
syncall/asana/asana_side.py
syncall/asana/asana_task.py
syncall/asana/utils.py
syncall/caldav/caldav_side.py
syncall/caldav/caldav_utils.py
syncall/cli.py
syncall/concrete_item.py
syncall/constants.py
syncall/exceptions.py
syncall/filesystem/filesystem_file.py
syncall/filesystem/filesystem_side.py
syncall/filesystem_gkeep_utils.py
syncall/google/__init__.py
syncall/google/common.py
syncall/google/gcal_side.py
syncall/google/gkeep_note.py
syncall/google/gkeep_note_side.py
syncall/google/gkeep_side.py
syncall/google/gkeep_todo_item.py
syncall/google/gkeep_todo_side.py
syncall/google/google_side.py
syncall/google/gtasks_side.py
syncall/notion/__init__.py
syncall/notion/notion_side.py
syncall/notion/notion_todo_block.py
syncall/pdb_cli_utils.py
syncall/res/gcal_client_secret.json
syncall/res/gtasks_client_secret.json
syncall/scripts/fs_gkeep_sync.py
syncall/scripts/tw_asana_sync.py
syncall/scripts/tw_caldav_sync.py
syncall/scripts/tw_gcal_sync.py
syncall/scripts/tw_gkeep_sync.py
syncall/scripts/tw_gtasks_sync.py
syncall/scripts/tw_notion_sync.py
syncall/side_helper.py
syncall/sync_side.py
syncall/taskwarrior/taskwarrior_side.py
syncall/tw_asana_utils.py
syncall/tw_caldav_utils.py
syncall/tw_gcal_utils.py
syncall/tw_gkeep_utils.py
syncall/tw_gtasks_utils.py
syncall/tw_notion_utils.py
syncall/tw_utils.py
syncall/types.py
syncall-1.8.8.dist-info/LICENSE
syncall-1.8.8.dist-info/METADATA
syncall-1.8.8.dist-info/WHEEL
syncall-1.8.8.dist-info/entry_points.txt
syncall-1.8.8.dist-info/RECORD
