Metadata-Version: 2.1
Name: syncall
Version: 1.8.8
Summary: Versatile bi-directional synchronization tool
Home-page: https://github.com/bergercookie/syncall
License: MIT
Keywords: asana,calendar,gkeep,google calendar,google keep,google tasks,google,notion,productivity,synchronization,task management,taskwarrior,caldav
Author: Nikos Koukis
Author-email: nickkouk@gmail.com
Requires-Python: >=3.8.1,<=3.12.5
Classifier: Environment :: Console
Classifier: Framework :: Pytest
Classifier: Intended Audience :: End Users/Desktop
Classifier: License :: OSI Approved :: MIT License
Classifier: Natural Language :: English
Classifier: Operating System :: Unix
Classifier: Programming Language :: Python
Classifier: Programming Language :: Python :: 3
Classifier: Programming Language :: Python :: 3.9
Classifier: Programming Language :: Python :: 3.10
Classifier: Programming Language :: Python :: 3.11
Classifier: Programming Language :: Python :: 3.12
Classifier: Programming Language :: Python :: 3 :: Only
Classifier: Programming Language :: Python :: 3.8
Classifier: Topic :: Utilities
Provides-Extra: asana
Provides-Extra: caldav
Provides-Extra: fs
Provides-Extra: gkeep
Provides-Extra: google
Provides-Extra: notion
Provides-Extra: tw
Requires-Dist: PyYAML (>=5.3.1,<5.4.0)
Requires-Dist: asana (>=1.0.0,<2.0.0) ; extra == "asana"
Requires-Dist: bidict (>=0.21.4,<0.22.0)
Requires-Dist: bubop (==0.1.12)
Requires-Dist: caldav (>=0.11.0,<0.12.0) ; extra == "caldav"
Requires-Dist: click (>=8.1.7,<9.0.0)
Requires-Dist: gkeepapi (>=0.13.7,<0.14.0) ; (python_version < "3.12") and (extra == "gkeep")
Requires-Dist: gkeepapi (>=0.16.0,<0.17.0) ; (python_full_version > "3.12.0") and (extra == "gkeep")
Requires-Dist: google-api-python-client (>=2.140.0,<3.0.0) ; extra == "google"
Requires-Dist: google-auth-oauthlib (>=0.4.6,<0.5.0) ; extra == "google"
Requires-Dist: icalendar (>=5.0.13,<6.0.0) ; extra == "caldav"
Requires-Dist: item-synchronizer (>=1.1.5,<2.0.0)
Requires-Dist: loguru (>=0.5.3,<0.6.0)
Requires-Dist: notion-client (>=0.7.1,<0.8.0) ; extra == "notion"
Requires-Dist: python-dateutil (>=2.9.0.post0,<3.0.0)
Requires-Dist: rfc3339 (>=6.2,<7.0)
Requires-Dist: setuptools (>=72.1.0,<73.0.0) ; (python_version >= "3.12") and (extra == "google")
Requires-Dist: taskw-ng (==0.2.7) ; extra == "tw"
Requires-Dist: xattr (>=0.9.9,<0.10.0) ; extra == "fs"
Requires-Dist: xdg (>=6.0.0,<7.0.0) ; extra == "tw"
Project-URL: Repository, https://github.com/bergercookie/syncall
